[
    {
        "op": "income",
        "amount": "14132.18",
        "category": "income",
        "description": "the origin balance",
        "time": "09/10/2024 23:03"
    },
    {
        "op": "income",
        "amount": "100",
        "category": "salary",
        "description": "work",
        "time": "09/10/2024 23:04"
    },
    {
        "op": "expense",
        "amount": "100",
        "category": "entertament",
        "description": "game",
        "time": "09/10/2024 23:15"
    }
]